ScotlandPYard/ScotlandPYard.py
ScotlandPYard/__init__.py
ScotlandPYard/cli.py
ScotlandPYard/mapcomponents.py
ScotlandPYard/profile_utils.py
ScotlandPYard/spymap.py
ScotlandPYard/config/__init__.py
ScotlandPYard/config/gameconfig.py
ScotlandPYard/resources/__init__.py
ScotlandPYard/resources/stylesheet.py
ScotlandPYard/resources/icons/cat.svg
ScotlandPYard/resources/icons/deer.svg
ScotlandPYard/resources/icons/dog.svg
ScotlandPYard/resources/icons/fox.svg
ScotlandPYard/resources/icons/frog.svg
ScotlandPYard/resources/icons/grasshopper.svg
ScotlandPYard/resources/icons/owl.svg
ScotlandPYard/resources/icons/panda.svg
ScotlandPYard/resources/icons/snail.svg
ScotlandPYard/resources/icons/walrus.svg
ScotlandPYard/resources/images/__init__.py
ScotlandPYard/resources/images/icon.png
ScotlandPYard/resources/images/map.jpg
ScotlandPYard/resources/images/map2.jpg
ScotlandPYard/resources/images/map3.jpg
ScotlandPYard/spyengine/StupidAIDetective.py
ScotlandPYard/spyengine/StupidAIMrX.py
ScotlandPYard/spyengine/__init__.py
ScotlandPYard/spyengine/abstractdetective.py
ScotlandPYard/spyengine/abstractmrx.py
ScotlandPYard/spyengine/abstractplayer.py
ScotlandPYard/spyengine/aidetective.py
ScotlandPYard/spyengine/aimrx.py
ScotlandPYard/spyengine/engine.py
ScotlandPYard/spyengine/humandetective.py
ScotlandPYard/spyengine/humanmrx.py
ScotlandPYard/spyengine/maputils.py
ScotlandPYard-1.4.1.dist-info/METADATA
ScotlandPYard-1.4.1.dist-info/RECORD
ScotlandPYard-1.4.1.dist-info/WHEEL
ScotlandPYard-1.4.1.dist-info/entry_points.txt
ScotlandPYard-1.4.1.dist-info/top_level.txt
