Metadata-Version: 2.1
Name: ScotlandPYard
Version: 1.4.1
Summary: A python implementation of the board game 'Scotland Yard'
Home-page: https://github.com/AhmadZakaria/ScotlandPYard
Author: Ahmad Zakaria Mohammad
Author-email: ahmadz1991@gmail.com
License: MIT license
Keywords: ScotlandPYard
Platform: UNKNOWN
Classifier: Development Status :: 2 - Pre-Alpha
Classifier: Intended Audience :: Developers
Classifier: License :: OSI Approved :: MIT License
Classifier: Natural Language :: English
Classifier: Programming Language :: Python :: 3.5
Classifier: Programming Language :: Python :: 3.6
Requires-Dist: Click (>=6.7)
Requires-Dist: networkx (==2.1)
Requires-Dist: numpy (==1.14.2)
Requires-Dist: PyQt5 (==5.10.1)
Requires-Dist: scipy (==1.0.1)
